authsimplified/__init__.py
authsimplified/admin.py
authsimplified/apps.py
authsimplified/managers.py
authsimplified/models.py
authsimplified/serializers.py
authsimplified/urls.py
authsimplified/utils.py
authsimplified/views.py
authsimplified-0.1.2.dist-info/METADATA
authsimplified-0.1.2.dist-info/WHEEL
authsimplified-0.1.2.dist-info/top_level.txt
authsimplified-0.1.2.dist-info/RECORD
