Metadata-Version: 2.4
Name: authsimplified
Version: 0.1.2
Summary: A simplified Django authentication package with email OTP verification.
Home-page: https://github.com/geoffowuor/authsimplified
Author: Geoffrey Owuor
Author-email: Geoffrey Owuor <geoffreyowuor71@gmail.com>
Requires-Python: >=3.8
Requires-Dist: django>=4.0
Requires-Dist: djangorestframework>=3.14
Requires-Dist: pyotp>=2.9
Dynamic: author
Dynamic: home-page
Dynamic: requires-python
